requirements_wayback_machine.py
requirements_wayback_machine-0.1.1.dist-info/LICENSE.txt
requirements_wayback_machine-0.1.1.dist-info/METADATA
requirements_wayback_machine-0.1.1.dist-info/WHEEL
requirements_wayback_machine-0.1.1.dist-info/entry_points.txt
requirements_wayback_machine-0.1.1.dist-info/top_level.txt
requirements_wayback_machine-0.1.1.dist-info/RECORD
