Metadata-Version: 2.1
Name: requirements-wayback-machine
Version: 0.1.1
Summary: Wayback machine for pip requirements.txt
Home-page: https://github.com/tkarabela/requirements-wayback-machine
Author: Tomas Karabela
Author-email: tkarabela@seznam.cz
License: MIT
Project-URL: Bug Tracker, https://github.com/tkarabela/requirements-wayback-machine/issues
Classifier: Development Status :: 4 - Beta
Classifier: Intended Audience :: Developers
Classifier: Intended Audience :: System Administrators
Classifier: License :: OSI Approved :: MIT License
Classifier: Operating System :: OS Independent
Classifier: Programming Language :: Python :: 3
Classifier: Programming Language :: Python :: 3.9
Classifier: Programming Language :: Python :: 3.10
Classifier: Programming Language :: Python :: 3.11
Classifier: Topic :: Software Development
Classifier: Topic :: Utilities
Classifier: Typing :: Typed
Requires-Python: >=3.9
License-File: LICENSE.txt
Requires-Dist: requests (~=2.28)
Requires-Dist: packaging (~=23.0)
